import_data/__init__.py
import_data/models.py
import_data/schema.rng
import_data/tests.py
import_data/management/__init__.py
import_data/management/commands/__init__.py
import_data/management/commands/process_xslt.py
import_data/management/commands/json_to_xml.py
import_data/management/commands/validate_xml.py
import_data/migrations/__init__.py
import_data/migrations/0001_initial.py
import_data/test_data/valid.xml
import_data/test_data/stackoverflow.html
import_data/test_data/valid.json
import_data/test_data/stackoverflow.xslt
django_import_data-0.4.2.dist-info/WHEEL
django_import_data-0.4.2.dist-info/RECORD
django_import_data-0.4.2.dist-info/DESCRIPTION.rst
django_import_data-0.4.2.dist-info/METADATA
django_import_data-0.4.2.dist-info/top_level.txt
django_import_data-0.4.2.dist-info/metadata.json
