Metadata-Version: 2.0
Name: django-import-data
Version: 0.4.2
Summary: A Django command line tool for importing HTML, XML and JSON data to models via XSLT mapping
Home-page: http://django-import-data.readthedocs.org
Author: Lev Veshnyakov
Author-email: lev@lev.website
License: MIT
Keywords: django import mapping parser xml html json xslt
Platform: UNKNOWN
Classifier: Development Status :: 3 - Alpha
Classifier: Intended Audience :: Developers
Classifier: Topic :: Software Development :: Build Tools
Classifier: License :: OSI Approved :: MIT License
Classifier: Programming Language :: Python :: 2.7
Classifier: Programming Language :: Python :: 3
Requires-Dist: lxml
Requires-Dist: django
Requires-Dist: dicttoxml
Provides-Extra: dev
Requires-Dist: pypandoc; extra == 'dev'
